alipayfanhua
