Metadata-Version: 1.0
Name: alipayfanhua
Version: 3.4.0
Summary: alipay sdk
Home-page: UNKNOWN
Author: fanhua
Author-email: 507303922@qq.com
License: MIT
Platform: UNKNOWN
